my_py_counter/__init__.py
my_py_counter/my_py_counter.py
my_py_counter/plotting.py
my_py_counter-0.1.0.dist-info/LICENSE
my_py_counter-0.1.0.dist-info/WHEEL
my_py_counter-0.1.0.dist-info/METADATA
my_py_counter-0.1.0.dist-info/RECORD
