Metadata-Version: 2.1
Name: my-py-counter
Version: 0.1.0
Summary: A python package to count number of words in a file
License: MIT
Author: Kazeem Omoloja
Requires-Python: >=3.9,<4.0
Classifier: License :: OSI Approved :: MIT License
Classifier: Programming Language :: Python :: 3
Classifier: Programming Language :: Python :: 3.10
Classifier: Programming Language :: Python :: 3.9
Requires-Dist: matplotlib (>=3.4.3,<4.0.0)
